multio/__init__.py
multio/_version.py
multio/constants.py
multio/lib.py
multio/metadata.py
multio/multio.py
multio/processed_multio.h
multio/utils.py
multio/plans/__init__.py
multio/plans/actions.py
multio/plans/base.py
multio/plans/plans.py
multio/plans/sinks.py
pymultio-2.8.0.9.dist-info/licenses/LICENSE
pymultio-2.8.0.9.dist-info/METADATA
pymultio-2.8.0.9.dist-info/WHEEL
pymultio-2.8.0.9.dist-info/top_level.txt
pymultio-2.8.0.9.dist-info/zip-safe
pymultio-2.8.0.9.dist-info/RECORD
