Metadata-Version: 2.4
Name: pymultio
Version: 2.8.0.9
Summary: A Python interface to multio.
Author-email: "European Centre for Medium-Range Weather Forecasts (ECMWF)" <software.support@ecmwf.int>
License-Expression: Apache-2.0
Project-URL: Homepage, https://github.com/ecmwf/multio/
Project-URL: Issues, https://github.com/ecmwf/multio/issues
Project-URL: Repository, https://github.com/ecmwf/multio/
Keywords: multio,multiopython,tools
Classifier: Development Status :: 4 - Beta
Classifier: Intended Audience :: Developers
Classifier: Programming Language :: Python :: 3
Classifier: Programming Language :: Python :: 3.5
Classifier: Programming Language :: Python :: 3.6
Classifier: Programming Language :: Python :: 3.7
Classifier: Programming Language :: Python :: Implementation :: CPython
Classifier: Programming Language :: Python :: Implementation :: PyPy
Classifier: Operating System :: OS Independent
Requires-Python: >=3.9
License-File: LICENSE
Requires-Dist: cffi
Requires-Dist: pydantic
Requires-Dist: pyyaml
Requires-Dist: numpy
Requires-Dist: findlibs
Provides-Extra: all
Requires-Dist: multiolib; extra == "all"
Provides-Extra: tests
Requires-Dist: pytest; extra == "tests"
Requires-Dist: pytest-cov; extra == "tests"
Requires-Dist: pytest-flakes; extra == "tests"
Dynamic: license-file
